gdrive_backup/__init__.py
gdrive_backup/apps.py
gdrive_backup/backup.py
gdrive_backup/backup_db.py
gdrive_backup/backup_local_files.py
gdrive_backup/backup_s3.py
gdrive_backup/base_backup.py
gdrive_backup/compression.py
gdrive_backup/enhanced_views.py
gdrive_backup/modals.py
gdrive_backup/prune_backups.py
gdrive_backup/sql_functions.py
gdrive_backup/tasks.py
gdrive_backup/urls.py
gdrive_backup/views.py
gdrive_backup/management/__init__.py
gdrive_backup/management/commands/__init__.py
gdrive_backup/management/commands/backup_website.py
gdrive_backup/management/commands/restore_db.py
gdrive_backup/templates/gdrive_backup/backup.html
gdrive_backup/templates/gdrive_backup/info.html
django_gdrive_backup-0.0.11.dist-info/LICENSE
django_gdrive_backup-0.0.11.dist-info/METADATA
django_gdrive_backup-0.0.11.dist-info/WHEEL
django_gdrive_backup-0.0.11.dist-info/top_level.txt
django_gdrive_backup-0.0.11.dist-info/RECORD
