Metadata-Version: 2.1
Name: django-gdrive-backup
Version: 0.0.11
Summary: Backs up django postgres databases, local folders and S3 folders to a Google Drive folder through a google service account.
Home-page: https://github.com/jonesim/django-gdrive-backup
Author: Ian Jones
Classifier: Programming Language :: Python :: 3
Classifier: License :: OSI Approved :: MIT License
Classifier: Operating System :: OS Independent
Requires-Python: >=3.6
License-File: LICENSE
Requires-Dist: encrypted-credentials
Requires-Dist: google-client-helper
Requires-Dist: requests
